odoo/addons/base_rest_external_id/README.rst
odoo/addons/base_rest_external_id/__init__.py
odoo/addons/base_rest_external_id/__manifest__.py
odoo/addons/base_rest_external_id/models/__init__.py
odoo/addons/base_rest_external_id/models/external_id_mixin.py
odoo12_addon_base_rest_external_id-12.0.1.0.2.dist-info/METADATA
odoo12_addon_base_rest_external_id-12.0.1.0.2.dist-info/WHEEL
odoo12_addon_base_rest_external_id-12.0.1.0.2.dist-info/top_level.txt
odoo12_addon_base_rest_external_id-12.0.1.0.2.dist-info/RECORD
